general_manager/__init__.py
general_manager/apps.py
general_manager/logging.py
general_manager/public_api_registry.py
general_manager/py.typed
general_manager/_types/__init__.py
general_manager/_types/api.py
general_manager/_types/bucket.py
general_manager/_types/cache.py
general_manager/_types/factory.py
general_manager/_types/general_manager.py
general_manager/_types/interface.py
general_manager/_types/manager.py
general_manager/_types/measurement.py
general_manager/_types/permission.py
general_manager/_types/rule.py
general_manager/_types/utils.py
general_manager/api/__init__.py
general_manager/api/graphql.py
general_manager/api/graphql_subscription_consumer.py
general_manager/api/mutation.py
general_manager/api/property.py
general_manager/bucket/__init__.py
general_manager/bucket/base_bucket.py
general_manager/bucket/calculation_bucket.py
general_manager/bucket/database_bucket.py
general_manager/bucket/group_bucket.py
general_manager/cache/__init__.py
general_manager/cache/cache_decorator.py
general_manager/cache/cache_tracker.py
general_manager/cache/dependency_index.py
general_manager/cache/model_dependency_collector.py
general_manager/cache/signals.py
general_manager/factory/__init__.py
general_manager/factory/auto_factory.py
general_manager/factory/factories.py
general_manager/factory/factory_methods.py
general_manager/interface/__init__.py
general_manager/interface/base_interface.py
general_manager/interface/orm_interface.py
general_manager/interface/bundles/__init__.py
general_manager/interface/bundles/calculation.py
general_manager/interface/bundles/database.py
general_manager/interface/capabilities/__init__.py
general_manager/interface/capabilities/base.py
general_manager/interface/capabilities/builtin.py
general_manager/interface/capabilities/configuration.py
general_manager/interface/capabilities/exceptions.py
general_manager/interface/capabilities/factory.py
general_manager/interface/capabilities/registry.py
generalmanager-0.27.1.dist-info/licenses/LICENSE
generalmanager-0.27.1.dist-info/METADATA
generalmanager-0.27.1.dist-info/WHEEL
generalmanager-0.27.1.dist-info/top_level.txt
generalmanager-0.27.1.dist-info/RECORD
