Metadata-Version: 2.4
Name: GeneralManager
Version: 0.27.1
Summary: Modular Django-based data management framework with ORM, GraphQL, fine-grained permissions, rule validation, calculations and caching.
Author-email: Tim Kleindick <tkleindick@yahoo.de>
License: MIT License
Project-URL: Homepage, https://github.com/TimKleindick/general_manager
Project-URL: Documentation, https://timkleindick.github.io/general_manager/
Project-URL: Repository, https://github.com/TimKleindick/general_manager
Project-URL: Issues, https://github.com/TimKleindick/general_manager/issues
Project-URL: Changelog, https://github.com/TimKleindick/general_manager/releases
Keywords: django,orm,graphql,permissions,validation,caching,framework
Classifier: License :: OSI Approved :: MIT License
Classifier: Programming Language :: Python :: 3
Classifier: Programming Language :: Python :: 3 :: Only
Classifier: Programming Language :: Python :: 3.12
Classifier: Programming Language :: Python :: 3.13
Classifier: Programming Language :: Python :: 3.14
Classifier: Framework :: Django
Classifier: Intended Audience :: Developers
Classifier: Operating System :: OS Independent
Classifier: Typing :: Typed
Requires-Python: >=3.12
License-File: LICENSE
Requires-Dist: asgiref>=3.8.1
Requires-Dist: celery<6.0.0,>=5.3.6
Requires-Dist: channels>=4.1.0
Requires-Dist: Django>=5.2.10
Requires-Dist: django-simple-history>=3.8.0
Requires-Dist: exrex>=0.12.0
Requires-Dist: factory_boy>=3.3.3
Requires-Dist: Faker>=37.1.0
Requires-Dist: flexcache>=0.3
Requires-Dist: flexparser>=0.4
Requires-Dist: gitdb>=4.0.12
Requires-Dist: GitPython>=3.1.41
Requires-Dist: graphene>=3.4.3
Requires-Dist: graphene-django>=3.2.3
Requires-Dist: graphql-core>=3.2.6
Requires-Dist: graphql-relay>=3.2.0
Requires-Dist: numpy>=2.2.5
Requires-Dist: Pint>=0.24.4
Requires-Dist: platformdirs>=4.3.7
Requires-Dist: promise>=2.3
Requires-Dist: python-dateutil>=2.9.0.post0
Requires-Dist: six>=1.17.0
Requires-Dist: smmap>=5.0.2
Requires-Dist: sqlparse>=0.5.3
Requires-Dist: text-unidecode>=1.3
Requires-Dist: typing_extensions>=4.13.2
Requires-Dist: tzdata>=2025.2
Dynamic: license-file
